knack/__init__.py
knack/_win_vt.py
knack/arguments.py
knack/cli.py
knack/commands.py
knack/completion.py
knack/config.py
knack/deprecation.py
knack/events.py
knack/experimental.py
knack/help.py
knack/help_files.py
knack/introspection.py
knack/invocation.py
knack/log.py
knack/output.py
knack/parser.py
knack/preview.py
knack/prompting.py
knack/query.py
knack/util.py
knack/validators.py
knack/testsdk/__init__.py
knack/testsdk/base.py
knack/testsdk/checkers.py
knack/testsdk/const.py
knack/testsdk/decorators.py
knack/testsdk/exceptions.py
knack/testsdk/patches.py
knack/testsdk/recording_processors.py
knack/testsdk/util.py
knack-0.11.0.dist-info/LICENSE
knack-0.11.0.dist-info/METADATA
knack-0.11.0.dist-info/WHEEL
knack-0.11.0.dist-info/top_level.txt
knack-0.11.0.dist-info/RECORD
