Metadata-Version: 2.1
Name: knack
Version: 0.11.0
Summary: A Command-Line Interface framework
Home-page: https://github.com/microsoft/knack
Author: Microsoft Corporation
Author-email: azpycli@microsoft.com
License: MIT
Classifier: Development Status :: 4 - Beta
Classifier: Intended Audience :: Developers
Classifier: Intended Audience :: System Administrators
Classifier: Programming Language :: Python
Classifier: Programming Language :: Python :: 3
Classifier: Programming Language :: Python :: 3.8
Classifier: Programming Language :: Python :: 3.9
Classifier: Programming Language :: Python :: 3.10
Classifier: Programming Language :: Python :: 3.11
Classifier: License :: OSI Approved :: MIT License
License-File: LICENSE
